<?xml version="1.0" encoding="utf-8"?>
<Monster xmlns:xsi="http://www.w3.org/2001/XMLSchema-instance" xmlns:xsd="http://www.w3.org/2001/XMLSchema">
  <Size>Medium</Size>
  <Name>Deathwisp</Name>
  <Descriptions />
  <Source>Tome of Beasts</Source>
  <Keywords>
    <Keyword>
      <Name>undead</Name>
    </Keyword>
  </Keywords>
  <Alignment>neutral evil</Alignment>
  <AC>15</AC>
  <HP>82</HP>
  <HPRoll>11d8 + 33</HPRoll>
  <Speeds>
    <string>0 ft.</string>
    <string>fly 60 ft. (hover)</string>
  </Speeds>
  <Strength>6</Strength>
  <Dexterity>20</Dexterity>
  <Constitution>16</Constitution>
  <Intelligence>18</Intelligence>
  <Wisdom>16</Wisdom>
  <Charisma>20</Charisma>
  <Resistances>
    <string>acid</string>
    <string>cold</string>
    <string>fire</string>
    <string>lightning</string>
    <string>thunder; bludgeoning</string>
    <string>piercing</string>
    <string>and slashing from nonmagical weapons that aren't silvered</string>
  </Resistances>
  <Vulnerablities />
  <Immunities>
    <string>necrotic</string>
    <string>poison</string>
  </Immunities>
  <ConditionImmunities>
    <string>charmed</string>
    <string>exhaustion</string>
    <string>grappled</string>
    <string>paralyzed</string>
    <string>petrified</string>
    <string>poisoned</string>
    <string>prone</string>
    <string>restrained</string>
  </ConditionImmunities>
  <Senses>
    <string>darkvision 60 ft.</string>
  </Senses>
  <PassivePerception>0</PassivePerception>
  <Languages>
    <string>the languages it knew in life</string>
  </Languages>
  <CR>7</CR>
  <XP>2900</XP>
  <Traits>
    <MonsterTrait>
      <Name>Flicker</Name>
      <Text>The deathwisp flickers in and out of sight, and ranged weapon attacks against it are made with disadvantage.</Text>
    </MonsterTrait>
    <MonsterTrait>
      <Name>Incorporeal Movement</Name>
      <Text>The deathwisp can move through other creatures and objects as if they were difficult terrain. It takes 5 (1d10) force damage if it ends its turn inside a solid object.</Text>
    </MonsterTrait>
    <MonsterTrait>
      <Name>Shadow Jump</Name>
      <Text>A deathwisp can travel between shadows as if by means of dimension door. This magical transport must begin and end in an area with at least some shadow. A shadow fey can jump up to a total of 40 feet per day; this may be a single jump of 40 feet, four jumps of 10 feet each, etc. This ability must be used in 10-foot increments.</Text>
    </MonsterTrait>
    <MonsterTrait>
      <Name>Sunlight Sensitivity</Name>
      <Text>While in sunlight, the deathwisp has disadvantage on attack rolls, as well as on Wisdom (Perception) checks that rely on sight.</Text>
    </MonsterTrait>
    <MonsterTrait>
      <Name>Unnatural Aura</Name>
      <Text>Animals do not willingly approach within 30 feet of a deathwisp, unless a master makes a successful DC 15 Wisdom (Animal Handling) check.</Text>
    </MonsterTrait>
  </Traits>
  <Actions>
    <MonsterAction>
      <Name>Life Drain</Name>
      <Text>Melee Weapon Attack: +8 to hit, reach 5 ft., one target. Hit: 36 (7d8 + 5) necrotic damage. The target must succeed on a DC 15 Constitution saving throw, or its hit point maximum is reduced by an amount equal to the damage taken. This reduction lasts until the target finishes a long rest. The target dies if this effect reduces its hit point maximum to 0.</Text>
      <AttackBonus>8</AttackBonus>
      <Damage>7d8 + 5</Damage>
    </MonsterAction>
    <MonsterTrait>
      <Name>Create Deathwisp</Name>
      <Text>The deathwisp targets a humanoid within 10 feet of it that died violently less than 1 minute ago. The target's spirit rises as a wraith in the space of its corpse or in the nearest unoccupied space. This wraith is under the deathwisp's control. The deathwisp can keep no more than five wraiths under its control at one time.</Text>
    </MonsterTrait>
  </Actions>
  <Reactions />
  <LegendaryActions />
  <SaveBonus>
    <MonsterSaveBonus>
      <Ability>Dexterity</Ability>
      <Bonus>3</Bonus>
    </MonsterSaveBonus>
    <MonsterSaveBonus>
      <Ability>Constitution</Ability>
      <Bonus>3</Bonus>
    </MonsterSaveBonus>
    <MonsterSaveBonus>
      <Ability>Wisdom</Ability>
      <Bonus>3</Bonus>
    </MonsterSaveBonus>
  </SaveBonus>
  <SkillBonus>
    <MonsterSkillBonus>
      <Skill>Perception</Skill>
      <Ability>None</Ability>
      <Bonus>3</Bonus>
      <Text />
    </MonsterSkillBonus>
    <MonsterSkillBonus>
      <Skill>Stealth</Skill>
      <Ability>None</Ability>
      <Bonus>3</Bonus>
      <Text />
    </MonsterSkillBonus>
  </SkillBonus>
  <Spells />
  <Slots />
</Monster>