<?xml version="1.0" encoding="utf-8"?>
<MagicProperty xmlns:xsi="http://www.w3.org/2001/XMLSchema-instance" xmlns:xsd="http://www.w3.org/2001/XMLSchema">
  <AttunementFeatures />
  <CarryFeatures>
    <Feature>
      <Keywords />
      <Name>Compass</Name>
      <Text>The wielder can use an action to learn which way is north.</Text>
      <Level>0</Level>
      <Hidden>false</Hidden>
      <NoDisplay>true</NoDisplay>
      <Action>Action</Action>
      <Prerequisite />
    </Feature>
  </CarryFeatures>
  <EquipFeatures />
  <AttunedEquipFeatures />
  <OnUseFeatures />
  <AttunedOnUseFeatures />
  <Name>Property - Compass</Name>
  <Description>The wielder can use an action to learn which way is north.</Description>
  <Slot>None</Slot>
  <Base>true</Base>
  <Source>Dungeon Master's Guide</Source>
  <PrependName>Guiding</PrependName>
  <Rarity>None</Rarity>
</MagicProperty>