<?xml version="1.0" encoding="utf-8"?>
<FeatureContainer xmlns:xsi="http://www.w3.org/2001/XMLSchema-instance" xmlns:xsd="http://www.w3.org/2001/XMLSchema">
  <Features>
    <Feature>
      <Keywords>
        <Keyword>
          <Name>mystic</Name>
        </Keyword>
        <Keyword>
          <Name>talent</Name>
        </Keyword>
      </Keywords>
      <Name>Light Step</Name>
      <Text>As a bonus action, you alter your density and weight to improve your mobility. For the rest of your turn, your walking speed increases by 10 feet, and the next time you stand up, you need to spend no more than 10 feet of movement to do so.</Text>
      <Level>0</Level>
      <Hidden>false</Hidden>
      <NoDisplay>false</NoDisplay>
      <Action>Bonus</Action>
      <Prerequisite />
    </Feature>
  </Features>
  <Source>Unearthed Arcana 6 - Psionics and the Mystic, Take 2</Source>
</FeatureContainer>