<?xml version="1.0" encoding="utf-8"?>
<Spell xmlns:xsi="http://www.w3.org/2001/XMLSchema-instance" xmlns:xsd="http://www.w3.org/2001/XMLSchema">
  <Keywords>
    <Keyword>
      <Name>verbal</Name>
    </Keyword>
    <Keyword>
      <Name>somatic</Name>
    </Keyword>
    <Keyword>
      <Name>bard</Name>
    </Keyword>
    <Keyword>
      <Name>sorcerer</Name>
    </Keyword>
    <Keyword>
      <Name>warlock</Name>
    </Keyword>
    <Keyword>
      <Name>wizard</Name>
    </Keyword>
    <Save>
      <Name>save</Name>
      <Throw>Intelligence</Throw>
    </Save>
    <Keyword>
      <Name>psychic</Name>
    </Keyword>
    <Keyword>
      <Name>sphere</Name>
    </Keyword>
    <Keyword>
      <Name>ranged</Name>
    </Keyword>
    <Keyword>
      <Name>instantaneous</Name>
    </Keyword>
    <Keyword>
      <Name>enchantment</Name>
    </Keyword>
  </Keywords>
  <CantripDamage />
  <Name>Synaptic Static</Name>
  <CastingTime>1 action</CastingTime>
  <Range>120 feet</Range>
  <Duration>Instantaneous</Duration>
  <Level>5</Level>
  <Description>You choose a point within range and cause psychic energy to explode there. Each creature in a 20-foot-radius sphere centered on that point must make an Intelligence saving throw. A creature with an Intelligence score of 2 or lower can’t be affected by this spell. A target takes 8d6 psychic damage on a failed save, or half as much damage on a successful one.
After a failed save, a target has muddled thoughts for 1 minute. During that time, it rolls a d6 and subtracts the number rolled from all its attack rolls and ability checks, as well as its Constitution saving throws to maintain concentration. The target can make an Intelligence saving throw at the end of each of its turns, ending the effect on itself on a success.</Description>
  <Descriptions />
  <Source>Xanathar’s Guide To Everything</Source>
</Spell>